epcis_dummy_generator/__init__.py
epcis_dummy_generator/companies.py
epcis_dummy_generator/items.py
epcis_dummy_generator/locations.py
epcis_dummy_generator/utils.py
epcis_dummy_generator-0.0.2.dist-info/METADATA
epcis_dummy_generator-0.0.2.dist-info/WHEEL
epcis_dummy_generator-0.0.2.dist-info/licenses/LICENSE
epcis_dummy_generator-0.0.2.dist-info/RECORD
