Metadata-Version: 2.3
Name: epcis_dummy_generator
Version: 0.0.2
Summary: A package for testing with EPCIS data.
Project-URL: Homepage, https://github.com/Violeta-Carvalho/EPCIS-Dummy-Generator
Project-URL: Issues, https://github.com/Violeta-Carvalho/EPCIS-Dummy-Generator/issues
Author-email: Violeta Carvalho <violetadecarvalho@gmail.com>
Classifier: License :: OSI Approved :: MIT License
Classifier: Operating System :: OS Independent
Classifier: Programming Language :: Python :: 3
Requires-Python: >=3.8
